pyclone/__init__.py
pyclone/log.py
pyclone/pyclone.py
PyClone-2020.9b2.dist-info/LICENSE
PyClone-2020.9b2.dist-info/METADATA
PyClone-2020.9b2.dist-info/WHEEL
PyClone-2020.9b2.dist-info/top_level.txt
PyClone-2020.9b2.dist-info/RECORD
