Metadata-Version: 2.1
Name: PyClone
Version: 2020.9b2
Summary: Wraps rclone and provides an interface for an installation at the host or container level.
Home-page: https://gitlab.com/ltgiv/pyclone
Author: Louis T. Getterman IV
Author-email: Thad@Getterman.org
License: MIT
Project-URL: Documentation, https://ltgiv.gitlab.io/pyclone/
Project-URL: Source, https://gitlab.com/ltgiv/pyclone
Project-URL: Tracker, https://gitlab.com/ltgiv/pyclone/issues
Platform: UNKNOWN
Classifier: Programming Language :: Python :: 3
Classifier: License :: OSI Approved :: MIT License
Classifier: Operating System :: POSIX
Classifier: Development Status :: 4 - Beta
Requires-Dist: Logbook
Requires-Dist: pexpect
Requires-Dist: arrow
